OpenInput/__init__.py
openinput-0.0.1.dist-info/LICENSE
openinput-0.0.1.dist-info/METADATA
openinput-0.0.1.dist-info/WHEEL
openinput-0.0.1.dist-info/top_level.txt
openinput-0.0.1.dist-info/RECORD
