Metadata-Version: 2.1
Name: openinput
Version: 0.0.1
Summary: OpenInput Used for Getting Inputs Easier!
Home-page: https://github.com/pypa/sampleproject
Author: Ariya Mirzaei
Author-email: mirzaeiariya88@gmail.com
License: UNKNOWN
Platform: UNKNOWN
Classifier: Programming Language :: Python :: 3
Classifier: License :: OSI Approved :: MIT License
Classifier: Operating System :: OS Independent
Requires-Python: >=3.6
